{"id":"2026_06_22_Argentina_vs_Austria","home":{"name":"Argentina","score":2,"color":"#74ACDF"},"away":{"name":"Austria","score":0,"color":"#ED2939"},"date":"2026-06-22","venue":"","stage":"Group Stage","xg":[2.34,0.65],"goals":[{"team":"home","min":37,"scorer":"Lionel Messi","assist":"Facundo Medina","pen":false,"own":false},{"team":"home","min":94,"scorer":"Lionel Messi","assist":null,"pen":false,"own":false}],"stats":[{"label":"Expected goals (xG)","h":2.34,"a":0.65,"fmt":"dec"},{"label":"Shots","h":12,"a":6},{"label":"Shots on target","h":8,"a":1},{"label":"Big chances","h":3,"a":1},{"label":"Passes completed","h":506,"a":423},{"label":"Pass accuracy","h":89,"a":84,"fmt":"pct"},{"label":"Dribbles won","h":6,"a":5},{"label":"Keeper saves","h":1,"a":7}],"shots":[{"team":"home","x":88.5,"y":50.0,"min":8,"player":"Lionel Messi","xg":0.777,"goal":false,"onTarget":false,"blocked":false,"body":"Left Foot","sit":"Penalty"},{"team":"away","x":92.3,"y":54.2,"min":22,"player":"Paul Wanner","xg":0.34,"goal":false,"onTarget":false,"blocked":false,"body":"Header","sit":"Open Play"},{"team":"away","x":88.3,"y":63.0,"min":22,"player":"Marcel Sabitzer","xg":0.067,"goal":false,"onTarget":false,"blocked":false,"body":"Left Foot","sit":"Open Play"},{"team":"home","x":86.7,"y":59.7,"min":31,"player":"Lionel Messi","xg":0.077,"goal":false,"onTarget":true,"blocked":false,"body":"Left Foot","sit":"Open Play"},{"team":"home","x":84.5,"y":54.7,"min":37,"player":"Lionel Messi","xg":0.102,"goal":true,"onTarget":true,"blocked":false,"body":"Left Foot","sit":"Fast Break"},{"team":"away","x":74.1,"y":42.4,"min":45,"player":"Marcel Sabitzer","xg":0.057,"goal":false,"onTarget":false,"blocked":false,"body":"Right Foot","sit":"Open Play"},{"team":"away","x":78.1,"y":77.2,"min":54,"player":"Marcel Sabitzer","xg":0.023,"goal":false,"onTarget":true,"blocked":false,"body":"Right Foot","sit":"Free Kick"},{"team":"home","x":80.2,"y":55.5,"min":61,"player":"Enzo Fernandez","xg":0.077,"goal":false,"onTarget":true,"blocked":false,"body":"Right Foot","sit":"Open Play"},{"team":"home","x":84.8,"y":63.3,"min":64,"player":"Lionel Messi","xg":0.077,"goal":false,"onTarget":false,"blocked":false,"body":"Left Foot","sit":"Open Play"},{"team":"away","x":93.0,"y":48.8,"min":66,"player":"Michael Gregoritsch","xg":0.101,"goal":false,"onTarget":false,"blocked":false,"body":"Header","sit":"Open Play"},{"team":"home","x":92.1,"y":53.4,"min":72,"player":"Nico Gonzalez","xg":0.34,"goal":false,"onTarget":false,"blocked":false,"body":"Header","sit":"Corner"},{"team":"home","x":86.6,"y":55.0,"min":85,"player":"Nico Gonzalez","xg":0.101,"goal":false,"onTarget":true,"blocked":false,"body":"Right Foot","sit":"Open Play"},{"team":"home","x":85.5,"y":49.7,"min":85,"player":"Enzo Fernandez","xg":0.102,"goal":false,"onTarget":true,"blocked":false,"body":"Right Foot","sit":"Open Play"},{"team":"away","x":92.1,"y":46.4,"min":92,"player":"Patrick Wimmer","xg":0.057,"goal":false,"onTarget":false,"blocked":false,"body":"Header","sit":"Set Piece"},{"team":"home","x":89.2,"y":57.7,"min":93,"player":"Julian Alvarez","xg":0.414,"goal":false,"onTarget":true,"blocked":false,"body":"Left Foot","sit":"Fast Break"},{"team":"home","x":90.4,"y":56.5,"min":94,"player":"Lionel Messi","xg":0.102,"goal":false,"onTarget":true,"blocked":false,"body":"Left Foot","sit":"Fast Break"},{"team":"home","x":96.9,"y":57.0,"min":94,"player":"Lionel Messi","xg":0.101,"goal":true,"onTarget":true,"blocked":false,"body":"Left Foot","sit":"Fast Break"},{"team":"home","x":71.4,"y":44.2,"min":97,"player":"Lionel Messi","xg":0.067,"goal":false,"onTarget":false,"blocked":false,"body":"Left Foot","sit":"Free Kick"}],"replays":[{"scorer":"Lionel Messi","min":37,"side":"home","assist":"Facundo Medina","xg":0.102,"players":4,"passes":4,"steps":[{"k":"pass","x":40.7,"y":2.5,"player":"Rodrigo De Paul","ex":53.1,"ey":11.2,"num":7},{"k":"pass","x":58.4,"y":25.9,"player":"Lionel Messi","ex":58.1,"ey":48.4,"num":10},{"k":"pass","x":76.2,"y":65.5,"player":"Thiago Almada","ex":90.4,"ey":82.3,"num":16},{"k":"pass","x":90.7,"y":81.7,"player":"Facundo Medina","ex":84.5,"ey":54.7,"num":25},{"k":"shot","x":84.5,"y":54.7,"player":"Lionel Messi","xg":0.102,"num":10}]},{"scorer":"Lionel Messi","min":94,"side":"home","assist":null,"xg":0.101,"players":1,"passes":1,"steps":[{"k":"pass","x":72.2,"y":14.7,"player":"Lionel Messi","ex":79.8,"ey":55.2,"num":10},{"k":"shot_eff","x":90.4,"y":56.5,"player":"Lionel Messi","xg":0.102,"num":10},{"k":"save","x":6.3,"y":45.3,"player":"Nicolas Seiwald","team":"away","num":6},{"k":"shot","x":96.9,"y":57.0,"player":"Lionel Messi","xg":0.101,"num":10}]}]}