{"id":"2026_07_04_1J_vs_2H","home":{"name":"Argentina","score":3,"color":"#74ACDF"},"away":{"name":"Cape Verde","score":2,"color":"#0033A0"},"date":"2026-07-03","venue":"Miami Stadium","stage":"Round of 32","xg":[2.37,0.61],"goals":[{"team":"home","min":28,"scorer":"Lionel Messi","assist":"Lisandro Martinez","pen":false,"own":false},{"team":"away","min":58,"scorer":"Deroy Duarte","assist":"Ryan Mendes","pen":false,"own":false},{"team":"home","min":91,"scorer":"Lisandro Martinez","assist":"Alexis Mac Allister","pen":false,"own":false},{"team":"away","min":102,"scorer":"Sidny Cabral","assist":"Yannick Semedo","pen":false,"own":false},{"team":"home","min":110,"scorer":"Diney Borges","assist":null,"pen":false,"own":true}],"stats":[{"label":"Expected goals (xG)","h":2.37,"a":0.61,"fmt":"dec"},{"label":"Shots","h":22,"a":16},{"label":"Shots on target","h":17,"a":11},{"label":"Big chances","h":3,"a":0},{"label":"Passes completed","h":805,"a":434},{"label":"Pass accuracy","h":91,"a":84,"fmt":"pct"},{"label":"Dribbles won","h":10,"a":12},{"label":"Keeper saves","h":9,"a":15}],"shots":[{"team":"away","x":85.2,"y":32.1,"min":6,"player":"Ryan Mendes","xg":0.052,"goal":false,"onTarget":true,"blocked":false,"body":"Left Foot","sit":"Fast Break","gy":49.2},{"team":"home","x":90.1,"y":68.9,"min":14,"player":"Lionel Messi","xg":0.045,"goal":false,"onTarget":false,"blocked":false,"body":"Left Foot","sit":"Open Play","gy":40.2},{"team":"home","x":74.1,"y":61.1,"min":17,"player":"Lionel Messi","xg":0.046,"goal":false,"onTarget":true,"blocked":false,"body":"Left Foot","sit":"Free Kick","gy":52.2},{"team":"home","x":96.5,"y":41.3,"min":28,"player":"Lionel Messi","xg":0.338,"goal":true,"onTarget":true,"blocked":false,"body":"Left Foot","sit":"Open Play","gy":46.4},{"team":"home","x":81.3,"y":53.5,"min":44,"player":"Enzo Fernandez","xg":0.082,"goal":false,"onTarget":true,"blocked":false,"body":"Right Foot","sit":"Open Play","gy":46.5},{"team":"away","x":77.1,"y":59.1,"min":48,"player":"Jovane Cabral","xg":0.045,"goal":false,"onTarget":true,"blocked":false,"body":"Right Foot","sit":"Corner","gy":50.6},{"team":"away","x":73.8,"y":30.1,"min":49,"player":"Ryan Mendes","xg":0.024,"goal":false,"onTarget":false,"blocked":false,"body":"Right Foot","sit":"Open Play","gy":56.5},{"team":"away","x":75.6,"y":47.4,"min":53,"player":"Deroy Duarte","xg":0.033,"goal":false,"onTarget":true,"blocked":false,"body":"Left Foot","sit":"Open Play","gy":48.0},{"team":"away","x":95.4,"y":33.8,"min":58,"player":"Deroy Duarte","xg":0.045,"goal":true,"onTarget":true,"blocked":false,"body":"Right Foot","sit":"Open Play","gy":52.0},{"team":"home","x":89.8,"y":44.6,"min":62,"player":"Lionel Messi","xg":0.525,"goal":false,"onTarget":true,"blocked":false,"body":"Right Foot","sit":"Open Play","gy":50.6},{"team":"home","x":86.5,"y":63.4,"min":66,"player":"Enzo Fernandez","xg":0.052,"goal":false,"onTarget":false,"blocked":false,"body":"Right Foot","sit":"Open Play","gy":31.6},{"team":"home","x":72.8,"y":47.1,"min":68,"player":"Lionel Messi","xg":0.041,"goal":false,"onTarget":true,"blocked":false,"body":"Left Foot","sit":"Free Kick","gy":49.6},{"team":"home","x":80.8,"y":61.9,"min":72,"player":"Lionel Messi","xg":0.096,"goal":false,"onTarget":true,"blocked":false,"body":"Left Foot","sit":"Free Kick","gy":48.4},{"team":"home","x":93.1,"y":47.8,"min":72,"player":"Nico Gonzalez","xg":0.068,"goal":false,"onTarget":false,"blocked":false,"body":"Header","sit":"Corner","gy":71.3},{"team":"away","x":68.2,"y":56.7,"min":77,"player":"Kevin Pina","xg":0.024,"goal":false,"onTarget":false,"blocked":false,"body":"Right Foot","sit":"Free Kick","gy":72.9},{"team":"home","x":94.0,"y":54.6,"min":83,"player":"Nico Gonzalez","xg":0.062,"goal":false,"onTarget":false,"blocked":false,"body":"Header","sit":"Corner","gy":36.8},{"team":"home","x":86.8,"y":32.5,"min":86,"player":"Alexis Mac Allister","xg":0.039,"goal":false,"onTarget":true,"blocked":false,"body":"Right Foot","sit":"Open Play","gy":49.0},{"team":"home","x":91.5,"y":47.0,"min":88,"player":"Alexis Mac Allister","xg":0.058,"goal":false,"onTarget":true,"blocked":false,"body":"Header","sit":"Open Play","gy":48.4},{"team":"home","x":71.5,"y":45.4,"min":91,"player":"Leandro Paredes","xg":0.024,"goal":false,"onTarget":true,"blocked":false,"body":"Right Foot","sit":"Open Play","gy":48.5},{"team":"home","x":77.7,"y":38.1,"min":94,"player":"Lionel Messi","xg":0.068,"goal":false,"onTarget":true,"blocked":false,"body":"Left Foot","sit":"Free Kick","gy":49.7},{"team":"home","x":91.5,"y":50.4,"min":94,"player":"Enzo Fernandez","xg":0.052,"goal":false,"onTarget":true,"blocked":false,"body":"Header","sit":"Set Piece","gy":48.7},{"team":"home","x":93.9,"y":33.1,"min":91,"player":"Lisandro Martinez","xg":0.041,"goal":true,"onTarget":true,"blocked":false,"body":"Left Foot","sit":"Corner","gy":46.8},{"team":"away","x":89.4,"y":52.7,"min":96,"player":"Diney Borges","xg":0.033,"goal":false,"onTarget":false,"blocked":false,"body":"Header","sit":"Corner","gy":67.9},{"team":"away","x":76.8,"y":50.5,"min":96,"player":"Steven Moreira","xg":0.052,"goal":false,"onTarget":true,"blocked":false,"body":"Right Foot","sit":"Corner","gy":49.9},{"team":"home","x":85.2,"y":57.9,"min":97,"player":"Lionel Messi","xg":0.094,"goal":false,"onTarget":true,"blocked":false,"body":"Left Foot","sit":"Open Play","gy":50.4},{"team":"home","x":90.6,"y":40.7,"min":97,"player":"Julian Alvarez","xg":0.082,"goal":false,"onTarget":true,"blocked":false,"body":"Right Foot","sit":"Open Play","gy":48.0},{"team":"home","x":81.9,"y":54.2,"min":98,"player":"Enzo Fernandez","xg":0.033,"goal":false,"onTarget":true,"blocked":false,"body":"Right Foot","sit":"Corner","gy":53.0},{"team":"away","x":85.8,"y":76.3,"min":102,"player":"Sidny Cabral","xg":0.033,"goal":true,"onTarget":true,"blocked":false,"body":"Right Foot","sit":"Open Play","gy":45.8},{"team":"home","x":84.7,"y":53.4,"min":105,"player":"Lionel Messi","xg":0.094,"goal":false,"onTarget":true,"blocked":false,"body":"Left Foot","sit":"Open Play","gy":48.3},{"team":"home","x":90.8,"y":41.1,"min":105,"player":"Gonzalo Montiel","xg":0.094,"goal":false,"onTarget":true,"blocked":false,"body":"Right Foot","sit":"Open Play","gy":51.4},{"team":"away","x":68.4,"y":69.6,"min":107,"player":"Yannick Semedo","xg":0.021,"goal":false,"onTarget":false,"blocked":false,"body":"Right Foot","sit":"Open Play","gy":66.4},{"team":"home","x":94.8,"y":55.4,"min":110,"player":"Cristian Romero","xg":0.338,"goal":false,"onTarget":false,"blocked":false,"body":"Header","sit":"Corner","gy":37.0},{"team":"away","x":93.2,"y":75.9,"min":113,"player":"Willy Semedo","xg":0.041,"goal":false,"onTarget":true,"blocked":false,"body":"Left Foot","sit":"Open Play","gy":51.0},{"team":"away","x":87.2,"y":81.2,"min":115,"player":"Sidny Cabral","xg":0.039,"goal":false,"onTarget":true,"blocked":false,"body":"Right Foot","sit":"Free Kick","gy":46.8},{"team":"away","x":87.0,"y":52.8,"min":118,"player":"Diney Borges","xg":0.033,"goal":false,"onTarget":true,"blocked":false,"body":"Header","sit":"Corner","gy":54.3},{"team":"away","x":80.3,"y":37.8,"min":120,"player":"Helio Varela","xg":0.068,"goal":false,"onTarget":true,"blocked":false,"body":"Right Foot","sit":"Open Play","gy":50.2},{"team":"away","x":82.2,"y":51.7,"min":121,"player":"Jamiro Monteiro","xg":0.039,"goal":false,"onTarget":true,"blocked":false,"body":"Right Foot","sit":"Corner","gy":53.3},{"team":"away","x":72.6,"y":40.1,"min":121,"player":"Helio Varela","xg":0.024,"goal":false,"onTarget":false,"blocked":false,"body":"Right Foot","sit":"Open Play","gy":63.0}],"replays":[{"scorer":"Lionel Messi","min":28,"side":"home","assist":"Lisandro Martinez","xg":0.338,"players":4,"passes":5,"steps":[{"k":"pass","x":65.7,"y":56.1,"player":"Lisandro Martinez","ex":65.7,"ey":29.8,"num":6},{"k":"pass","x":63.5,"y":24.7,"player":"Cristian Romero","ex":72.8,"ey":6.6,"num":13},{"k":"pass","x":70.1,"y":8.2,"player":"Nahuel Molina","ex":54.1,"ey":10.2,"num":26},{"k":"pass","x":55.0,"y":15.7,"player":"Cristian Romero","ex":54.8,"ey":49.3,"num":13},{"k":"pass","x":55.7,"y":54.8,"player":"Lisandro Martinez","ex":91.9,"ey":38.9,"num":6},{"k":"shot","x":96.5,"y":41.3,"player":"Lionel Messi","xg":0.338,"num":10}]},{"scorer":"Deroy Duarte","min":58,"side":"away","assist":"Ryan Mendes","xg":0.045,"players":4,"passes":3,"steps":[{"k":"pass","x":60.8,"y":40.0,"player":"Pico Lopes","ex":65.6,"ey":28.6,"num":4},{"k":"pass","x":75.3,"y":37.0,"player":"Steven Moreira","ex":90.6,"ey":10.6,"num":22},{"k":"pass","x":93.7,"y":17.8,"player":"Ryan Mendes","ex":93.5,"ey":35.2,"num":20},{"k":"shot","x":95.4,"y":33.8,"player":"Deroy Duarte","xg":0.045,"num":14}]},{"scorer":"Lisandro Martinez","min":91,"side":"home","assist":"Alexis Mac Allister","xg":0.041,"players":3,"passes":2,"steps":[{"k":"pass","x":99.5,"y":99.5,"player":"Lionel Messi","ex":94.4,"ey":61.6,"cross":true,"num":10},{"k":"pass","x":94.4,"y":61.6,"player":"Alexis Mac Allister","ex":94.9,"ey":29.7,"num":20},{"k":"shot","x":93.9,"y":33.1,"player":"Lisandro Martinez","xg":0.041,"num":6}]},{"scorer":"Sidny Cabral","min":102,"side":"away","assist":"Yannick Semedo","xg":0.033,"players":8,"passes":12,"steps":[{"k":"pass","x":4.3,"y":45.2,"player":"Vozinha","ex":13.5,"ey":27.4,"num":1},{"k":"pass","x":13.0,"y":27.8,"player":"Yannick Semedo","ex":14.2,"ey":40.3,"num":16},{"k":"pass","x":11.8,"y":39.1,"player":"Pico Lopes","ex":30.8,"ey":13.2,"num":4},{"k":"pass","x":32.2,"y":11.7,"player":"Steven Moreira","ex":44.5,"ey":3.8,"num":22},{"k":"pass","x":37.4,"y":7.1,"player":"Willy Semedo","ex":34.4,"ey":25.3,"num":17},{"k":"pass","x":37.2,"y":28.3,"player":"Yannick Semedo","ex":39.7,"ey":50.9,"num":16},{"k":"pass","x":39.2,"y":47.9,"player":"Jamiro Monteiro","ex":49.3,"ey":78.1,"num":10},{"k":"pass","x":57.6,"y":88.4,"player":"Sidny Cabral","ex":69.8,"ey":93.8,"num":13},{"k":"pass","x":81.1,"y":84.7,"player":"Helio Varela","ex":87.8,"ey":91.8,"num":26},{"k":"pass","x":86.4,"y":93.8,"player":"Sidny Cabral","ex":71.2,"ey":78.5,"num":13},{"k":"pass","x":71.1,"y":76.4,"player":"Jamiro Monteiro","ex":65.6,"ey":50.3,"num":10},{"k":"pass","x":69.8,"y":57.5,"player":"Yannick Semedo","ex":87.3,"ey":87.9,"num":16},{"k":"dribble","x":89.0,"y":83.4,"player":"Sidny Cabral","num":13},{"k":"shot","x":85.8,"y":76.3,"player":"Sidny Cabral","xg":0.033,"num":13}]},{"scorer":"Own goal","min":110,"side":"home","assist":null,"xg":null,"players":1,"passes":1,"steps":[{"k":"pass","x":99.5,"y":99.5,"player":"Lionel Messi","ex":94.8,"ey":55.4,"cross":true,"num":10},{"k":"shot","x":95.4,"y":52.8,"player":"Diney Borges","og":true,"num":3}],"own":true,"ogBy":"Diney Borges"}]}